dask_awkward/__init__.py
dask_awkward/awkward.yaml
dask_awkward/config.py
dask_awkward/pickle.py
dask_awkward/py.typed
dask_awkward/utils.py
dask_awkward/version.py
dask_awkward/version.pyi
dask_awkward/layers/__init__.py
dask_awkward/layers/layers.py
dask_awkward/lib/__init__.py
dask_awkward/lib/core.py
dask_awkward/lib/describe.py
dask_awkward/lib/inspect.py
dask_awkward/lib/operations.py
dask_awkward/lib/optimize.py
dask_awkward/lib/reducers.py
dask_awkward/lib/str.py
dask_awkward/lib/structure.py
dask_awkward/lib/testutils.py
dask_awkward/lib/unproject_layout.py
dask_awkward/lib/utils.py
dask_awkward/lib/io/__init__.py
dask_awkward/lib/io/columnar.py
dask_awkward/lib/io/io.py
dask_awkward/lib/io/json.py
dask_awkward/lib/io/parquet.py
dask_awkward/lib/io/text.py
dask_awkward/manual/__init__.py
dask_awkward/manual/column_optimization.py
dask_awkward_sizeof/__init__.py
dask_awkward-2025.9.0.dist-info/METADATA
dask_awkward-2025.9.0.dist-info/WHEEL
dask_awkward-2025.9.0.dist-info/entry_points.txt
dask_awkward-2025.9.0.dist-info/licenses/LICENSE
dask_awkward-2025.9.0.dist-info/RECORD
